crsml/__init__.py
crsml/crsml.py
crsml-1.2.2.dist-info/LICENSE
crsml-1.2.2.dist-info/METADATA
crsml-1.2.2.dist-info/WHEEL
crsml-1.2.2.dist-info/top_level.txt
crsml-1.2.2.dist-info/RECORD
