Metadata-Version: 2.1
Name: crsml
Version: 1.2.2
Summary: This is my personal toolkit.
Home-page: https://github.com/wsywddr
Author: Chris Chen
Author-email: wsywddr@163.com
License: UNKNOWN
Platform: UNKNOWN
Classifier: Programming Language :: Python :: 3
Classifier: License :: OSI Approved :: MIT License
Classifier: Operating System :: OS Independent
Requires-Dist: scikit-learn (==0.21.2)
Requires-Dist: scikit-plot (==0.3.7)
